sanic_swagger_37/__init__.py
sanic_swagger_37/doc.py
sanic_swagger_37/openapi.py
sanic_swagger_37/options.py
sanic_swagger_37/serializer.py
sanic_swagger_37/swagger.py
sanic_swagger_37/validators.py
sanic_swagger_37/ui/favicon-16x16.png
sanic_swagger_37/ui/favicon-32x32.png
sanic_swagger_37/ui/index.html
sanic_swagger_37/ui/oauth2-redirect.html
sanic_swagger_37-0.0.2.dist-info/DESCRIPTION.rst
sanic_swagger_37-0.0.2.dist-info/METADATA
sanic_swagger_37-0.0.2.dist-info/RECORD
sanic_swagger_37-0.0.2.dist-info/WHEEL
sanic_swagger_37-0.0.2.dist-info/metadata.json
sanic_swagger_37-0.0.2.dist-info/top_level.txt
